hotel_mcp_server.py
mcp_hotel_search-0.1.2.dist-info/licenses/LICENSE
mcp_hotel_search-0.1.2.dist-info/METADATA
mcp_hotel_search-0.1.2.dist-info/WHEEL
mcp_hotel_search-0.1.2.dist-info/entry_points.txt
mcp_hotel_search-0.1.2.dist-info/top_level.txt
mcp_hotel_search-0.1.2.dist-info/RECORD
