Metadata-Version: 2.4
Name: mcp-hotel-search
Version: 0.1.2
Summary: Hotel search service built with Google's Agent Developer Kit (ADK) and MCP
Author-email: Arjun Prabhulal <code.aicloudlab@gmail.com>
License: MIT License
Project-URL: Homepage, https://github.com/arjunprabhulal/mcp-hotel-search
Project-URL: Bug Tracker, https://github.com/arjunprabhulal/mcp-hotel-search/issues
Classifier: Development Status :: 3 - Alpha
Classifier: Intended Audience :: Developers
Classifier: License :: OSI Approved :: MIT License
Classifier: Programming Language :: Python :: 3
Classifier: Programming Language :: Python :: 3.9
Classifier: Programming Language :: Python :: 3.10
Classifier: Programming Language :: Python :: 3.11
Requires-Python: >=3.9
License-File: LICENSE
Requires-Dist: google-search-results
Requires-Dist: google-adk
Requires-Dist: mcp
Dynamic: license-file
